{
  "main": {
    "id": "35b5c12fa43d550e",
    "type": "split",
    "children": [
      {
        "id": "d57497b628efa209",
        "type": "tabs",
        "children": [
          {
            "id": "afc19bb0c571acb5",
            "type": "leaf",
            "state": {
              "type": "markdown",
              "state": {
                "file": "Computer Science 122/Exam 1 Review Guide.md",
                "mode": "preview",
                "source": true
              }
            }
          },
          {
            "id": "852bda0b784a4d9d",
            "type": "leaf",
            "state": {
              "type": "excalidraw",
              "state": {
                "file": "Calculus III/Excalidraw/1. Review/Review Graphic 1.md"
              }
            }
          },
          {
            "id": "87a4d9903aa5887e",
            "type": "leaf",
            "state": {
              "type": "excalidraw",
              "state": {
                "file": "Calculus III/Excalidraw/7. Functions of 2 or more variables/7. Functions of 2 or more variables 2024-02-01 08.57.38.excalidraw.md"
              }
            }
          },
          {
            "id": "541040fe8c1784df",
            "type": "leaf",
            "state": {
              "type": "excalidraw",
              "state": {
                "file": "Calculus III/Excalidraw/7. Functions of 2 or more variables/7. Functions of 2 or more variables 2024-02-01 08.44.30.excalidraw.md"
              }
            }
          }
        ]
      }
    ],
    "direction": "vertical"
  },
  "left": {
    "id": "f7ac9c95f399e3aa",
    "type": "split",
    "children": [
      {
        "id": "09049eec32dab478",
        "type": "tabs",
        "children": [
          {
            "id": "b7e912c672634f3e",
            "type": "leaf",
            "state": {
              "type": "file-explorer",
              "state": {
                "sortOrder": "alphabetical"
              }
            }
          },
          {
            "id": "67b5173d86ef6d3d",
            "type": "leaf",
            "state": {
              "type": "search",
              "state": {
                "query": "",
                "matchingCase": false,
                "explainSearch": false,
                "collapseAll": false,
                "extraContext": false,
                "sortOrder": "alphabetical"
              }
            }
          },
          {
            "id": "cdfc33cd6f91274f",
            "type": "leaf",
            "state": {
              "type": "bookmarks",
              "state": {}
            }
          }
        ]
      }
    ],
    "direction": "horizontal",
    "width": 219.5
  },
  "right": {
    "id": "489dec59a85c3480",
    "type": "split",
    "children": [
      {
        "id": "b2947c7739813161",
        "type": "tabs",
        "children": [
          {
            "id": "3fa58907c03d6013",
            "type": "leaf",
            "state": {
              "type": "backlink",
              "state": {
                "file": "Computer Science 122/Exam 1 Review Guide.md",
                "collapseAll": false,
                "extraContext": false,
                "sortOrder": "alphabetical",
                "showSearch": false,
                "searchQuery": "",
                "backlinkCollapsed": false,
                "unlinkedCollapsed": true
              }
            }
          },
          {
            "id": "cda3ecd2c8f7dcc4",
            "type": "leaf",
            "state": {
              "type": "outgoing-link",
              "state": {
                "file": "Computer Science 122/Exam 1 Review Guide.md",
                "linksCollapsed": false,
                "unlinkedCollapsed": true
              }
            }
          },
          {
            "id": "13f3cef8b65cddab",
            "type": "leaf",
            "state": {
              "type": "tag",
              "state": {
                "sortOrder": "frequency",
                "useHierarchy": true
              }
            }
          },
          {
            "id": "8a1e302c308ead3c",
            "type": "leaf",
            "state": {
              "type": "outline",
              "state": {
                "file": "Computer Science 122/Exam 1 Review Guide.md"
              }
            }
          },
          {
            "id": "eaffc4925a87ff86",
            "type": "leaf",
            "state": {
              "type": "git-view",
              "state": {}
            }
          }
        ],
        "currentTab": 4
      }
    ],
    "direction": "horizontal",
    "width": 200
  },
  "left-ribbon": {
    "hiddenItems": {
      "switcher:Open quick switcher": false,
      "graph:Open graph view": false,
      "canvas:Create new canvas": false,
      "daily-notes:Open today's daily note": false,
      "templates:Insert template": false,
      "command-palette:Open command palette": false,
      "obsidian-excalidraw-plugin:Create new drawing": false
    }
  },
  "active": "afc19bb0c571acb5",
  "lastOpenFiles": [
    "Calculus III/7. Functions of 2 or more variables.md",
    "Computer Science 122/Exam 1 Review Guide.md",
    "APUSH/APUSH Daily Journal.md",
    "Calculus III/Excalidraw/7. Functions of 2 or more variables/7. Functions of 2 or more variables 2024-02-01 08.20.08.excalidraw.md",
    "Calculus III/6. Arc Length and Curvature.md",
    "Calculus III/5. Tangent Vectors.md",
    "Calculus III/1. Review.md",
    "Calculus III/Excalidraw/1. Review/Review Graphic 1.md",
    "Calculus III/2. Lines, Planes and Vectors.md",
    "Calculus III/3. Conic Sections and 3-D Surfaces.md",
    "Calculus III/4. 3-D Graphs from Traces.md",
    "Calculus III/Excalidraw/7. Functions of 2 or more variables/7. Functions of 2 or more variables 2024-02-01 08.57.38.excalidraw.md",
    "Calculus III/Excalidraw/7. Functions of 2 or more variables/7. Functions of 2 or more variables 2024-02-01 08.44.30.excalidraw.md",
    "Calculus III/Excalidraw/7. Functions of 2 or more variables/7. Functions of 2 or more variables 2024-02-01 08.34.51.excalidraw.md",
    "Calculus III/Excalidraw/6. Arc Length and Curvature/6. 2024-01-30 08.53.08.excalidraw.md",
    "Calculus III/Excalidraw/7. Functions of 2 or more variables",
    "AP Computer Science/Unit 1/1.5 Casting and Range of Variables.md",
    "AP Chemistry/Unit 6/6.4 Covalent Bonding & Lewis Structures.md",
    "AP Chemistry/Unit 6/6.5 Formal Charge.md",
    "AP Chemistry/Unit 6/6.3 Ionic & Covalent Naming.md",
    "AP Chemistry/Unit 6/6.1 Metallic Bonding & Alloys.md",
    "Computer Science 121/Computer Science Notes/12.2 Recursion II.md",
    "Computer Science 121/Computer Science Notes/12.1 Recursion I.md",
    "Computer Science 121/Computer Science Notes/13.2 Bits and Operations II.md",
    "Computer Science 121/Computer Science Notes/14.1 Dynamic Data Structures I.md",
    "Computer Science 121/Computer Science Notes/13.1 Bits and Operations.md",
    "Computer Science 121/Computer Science Notes/Exam 2 Review Guide.md",
    "AP Computer Science/Unit 2",
    "AP Chemistry/Unit 8/Images/Ice Heating Curve Labelled.png",
    "AP Chemistry/Unit 8/Images/Ice Heating Curve.png",
    "Calculus III/Excalidraw/6. Arc Length and Curvature",
    "Calculus III/Excalidraw/5. Tangent Vectors",
    "Calculus III/Excalidraw/4. 3-D Graphs from Traces",
    "Computer Science 122/Excalidraw",
    "Linear Algebra/ProfPDFs/Week 3.pdf",
    "Linear Algebra/ProfPDFs/Week 2.pdf",
    "Linear Algebra/ProfPDFs/Week 1.pdf",
    "Linear Algebra/ProfPDFs",
    "AP Chemistry/Unit 7/Images/CCL4 Lewis Structure.png",
    "AP Chemistry/Unit 7/Images/H2S Lewis Structure.png",
    "AP Chemistry/Unit 7/Images/HF Lewis Structure.png",
    "AP Chemistry/Unit 8/Images/Ice Heating Curve 1.png",
    "About/Find a Resource.canvas",
    "AP Chemistry/Images/Periodic Table of Elements.png",
    "AP Chemistry/Unit 6/Images/Square Planar Molecular Geometry.png",
    "AP Chemistry/Unit 6/Images/Trigonal Pyramidal Molecular Geometry.png",
    "AP Chemistry/Unit 6/Images/Tetrahedral Molecular Geometry.png",
    "Untitled.canvas"
  ]
}